imgcrop/__init__.py
imgcrop/imgcrop.py
imgcrop-0.1.0.dist-info/LICENSE
imgcrop-0.1.0.dist-info/METADATA
imgcrop-0.1.0.dist-info/WHEEL
imgcrop-0.1.0.dist-info/top_level.txt
imgcrop-0.1.0.dist-info/RECORD
