Metadata-Version: 2.1
Name: imgcrop
Version: 0.1.0
Summary: Simple image augmentation library focusing on random geometric cropping.
Home-page: https://github.com/yu4u/imgcrop
Author: Yusuke Uchida
Author-email: ren4yu@gmail.com
License: MIT
Keywords: augmentation,image,deep learning,neural network,machine learning
Platform: UNKNOWN
Classifier: License :: OSI Approved :: MIT License
Classifier: Intended Audience :: Developers
Classifier: Intended Audience :: Science/Research
Classifier: Operating System :: OS Independent
Classifier: Programming Language :: Python
Classifier: Programming Language :: Python :: 3
Classifier: Programming Language :: Python :: 3.4
Classifier: Programming Language :: Python :: 3.5
Classifier: Programming Language :: Python :: 3.6
Classifier: Programming Language :: Python :: 3.7
Classifier: Topic :: Software Development :: Libraries
Classifier: Topic :: Software Development :: Libraries :: Python Modules
Requires-Dist: numpy
Requires-Dist: opencv-python
